{
    "loadBalancerAudits":[
        {"id":123,"status":"ERROR","created":"2011-04-14T15:53:06-05:00",
            "updated":"2011-04-14T15:53:06-05:00","alertAudits":[
            {"alerts":[]}]},
        {"id":379,"status":"ERROR","created":"2011-05-03T12:58:09-05:00",
            "updated":"2011-05-03T12:58:10-05:00","alertAudits":[
            {"alerts":[]}]},
        {"id":380,"status":"ERROR","created":"2011-05-03T13:21:33-05:00",
            "updated":"2011-05-03T13:21:35-05:00","alertAudits":[
            {"alerts":[]}]},
        {"id":435,"status":"ERROR","created":"2011-05-13T12:12:48-05:00",
            "updated":"2011-05-13T12:12:54-05:00","alertAudits":[
            {"alerts":[
                {"id":1,"status":"UNACKNOWLEDGED","accountId":563374, "loadbalancerId":435,
                    "created":"2011-05-13T12:12:54-05:00","messageName":"An error occurred while creating loadbalancer '435' in Zeus."}]}]},
        {"id":437,"status":"ERROR","created":"2011-05-13T12:23:30-05:00",
            "updated":"2011-05-13T12:23:35-05:00","alertAudits":[
            {"alerts":[
                {"id":2,"status":"UNACKNOWLEDGED","accountId":563374,"loadbalancerId":437,
                    "created":"2011-05-13T12:23:35-05:00","messageName":"An error occurred while creating loadbalancer '437' in Zeus."}]}]}]
}